GooseMPL/__init__.py
GooseMPL/_version.py
GooseMPL-0.15.1.dist-info/LICENSE
GooseMPL-0.15.1.dist-info/METADATA
GooseMPL-0.15.1.dist-info/WHEEL
GooseMPL-0.15.1.dist-info/top_level.txt
GooseMPL-0.15.1.dist-info/RECORD
