Metadata-Version: 2.1
Name: GooseMPL
Version: 0.15.1
Summary: Style and extension functions for matplotlib
Author-email: Tom de Geus <tom@geus.me>
Project-URL: Source, https://github.com/tdegeus/GooseMPL
Classifier: License :: OSI Approved :: MIT License
Requires-Python: >=3.6
License-File: LICENSE
Requires-Dist: deprecation
Requires-Dist: matplotlib
Requires-Dist: numpy
Requires-Dist: pyyaml
Requires-Dist: scipy
